.bumpversion.cfg
.cookiecutterrc
.coveragerc
.editorconfig
.gitignore
AUTHORS.rst
CHANGELOG.rst
CONTRIBUTING.rst
LICENSE
MANIFEST.in
README.md
setup.cfg
setup.py
tox.ini
ci/bootstrap.py
ci/templates/.travis.yml
ci/templates/tox.ini
docs/authors.rst
docs/changelog.rst
docs/conf.py
docs/contributing.rst
docs/index.rst
docs/installation.rst
docs/readme.rst
docs/requirements.txt
docs/spelling_wordlist.txt
docs/usage.rst
docs/reference/index.rst
docs/reference/leopy.rst
src/.DS_Store
src/demo/AriesMacOS.md
src/demo/FaberAliceCredential.md
src/demo/echoer.py
src/leopy/__init__.py
src/leopy/__main__.py
src/leopy/cli.py
src/leopy/daemon.py
src/leopy/leopying.py
src/leopy.egg-info/PKG-INFO
src/leopy.egg-info/SOURCES.txt
src/leopy.egg-info/dependency_links.txt
src/leopy.egg-info/entry_points.txt
src/leopy.egg-info/not-zip-safe
src/leopy.egg-info/requires.txt
src/leopy.egg-info/top_level.txt
src/leopy/core/__init__.py
src/leopy/core/resting.py
src/leopy/end/__init__.py
src/leopy/end/ending.py
src/leopy/flo/main.flo
src/leopy/static/service/event_service.js
src/leopy/static/service/server-event.service.coffee
src/leopy/static/service/server-event.service.js
tests/test_leopy.py