Metadata-Version: 1.2
Name: leopy
Version: 0.1.6
Summary: Hyperledger Aries Cloud Agent Controller Demo
Home-page: https://github.com/SmithSamuelM/leopy
Author: Samuel M. Smith
Author-email: smith.samuel.m@gmail.com
License: Apache Software License 2.0
Project-URL: Documentation, https://leopy.readthedocs.io/
Project-URL: Changelog, https://leopy.readthedocs.io/en/latest/changelog.html
Project-URL: Issue Tracker, https://github.com/SmithSamuelM/leopy/issues
Platform: UNKNOWN
Classifier: Development Status :: 4 - Beta
Classifier: Intended Audience :: Developers
Classifier: License :: OSI Approved :: Apache Software License
Classifier: Operating System :: Unix
Classifier: Operating System :: POSIX
Classifier: Operating System :: Microsoft :: Windows
Classifier: Programming Language :: Python :: 3.7
Classifier: Programming Language :: Python :: Implementation :: CPython
Classifier: Topic :: Utilities
Requires-Python: >=3.7
